odoo/addons/purchase_order_product_recommendation_xlsx/README.rst
odoo/addons/purchase_order_product_recommendation_xlsx/__init__.py
odoo/addons/purchase_order_product_recommendation_xlsx/__manifest__.py
odoo/addons/purchase_order_product_recommendation_xlsx/i18n/es.po
odoo/addons/purchase_order_product_recommendation_xlsx/i18n/it.po
odoo/addons/purchase_order_product_recommendation_xlsx/i18n/purchase_order_product_recommendation_xlsx.pot
odoo/addons/purchase_order_product_recommendation_xlsx/readme/CONTRIBUTORS.md
odoo/addons/purchase_order_product_recommendation_xlsx/readme/DESCRIPTION.md
odoo/addons/purchase_order_product_recommendation_xlsx/readme/USAGE.md
odoo/addons/purchase_order_product_recommendation_xlsx/report/__init__.py
odoo/addons/purchase_order_product_recommendation_xlsx/report/recommendation_xlsx.py
odoo/addons/purchase_order_product_recommendation_xlsx/report/recommendation_xlsx.xml
odoo/addons/purchase_order_product_recommendation_xlsx/static/description/icon.png
odoo/addons/purchase_order_product_recommendation_xlsx/static/description/index.html
odoo/addons/purchase_order_product_recommendation_xlsx/tests/__init__.py
odoo/addons/purchase_order_product_recommendation_xlsx/tests/test_recommendation.py
odoo/addons/purchase_order_product_recommendation_xlsx/wizards/__init__.py
odoo/addons/purchase_order_product_recommendation_xlsx/wizards/purchase_order_recommendation.py
odoo/addons/purchase_order_product_recommendation_xlsx/wizards/purchase_order_recommendation_view.xml
odoo_addon_purchase_order_product_recommendation_xlsx-18.0.1.0.0.4.dist-info/METADATA
odoo_addon_purchase_order_product_recommendation_xlsx-18.0.1.0.0.4.dist-info/WHEEL
odoo_addon_purchase_order_product_recommendation_xlsx-18.0.1.0.0.4.dist-info/top_level.txt
odoo_addon_purchase_order_product_recommendation_xlsx-18.0.1.0.0.4.dist-info/RECORD
